zzq/__init__.py
zzq/zzq.py
zzq-1.3.dist-info/LICENSE
zzq-1.3.dist-info/METADATA
zzq-1.3.dist-info/WHEEL
zzq-1.3.dist-info/top_level.txt
zzq-1.3.dist-info/RECORD
