Metadata-Version: 2.1
Name: zzq
Version: 1.3
Summary: zzq very smart
Author: XZH100
Author-email: cc@qq.com
Requires-Python: >=3.6
License-File: LICENSE
